CBDict/__init__.py
CBDict-2.0.dist-info/LICENSE
CBDict-2.0.dist-info/METADATA
CBDict-2.0.dist-info/WHEEL
CBDict-2.0.dist-info/entry_points.txt
CBDict-2.0.dist-info/top_level.txt
CBDict-2.0.dist-info/RECORD
