Metadata-Version: 2.1
Name: CBDict
Version: 2.0
Summary: This program monitors the clipboard of the system and translate the word from English to Chinese by YouDao api, especially designed for Students who are working under linux environment where there is no simple translater when you reading papers.
Home-page: https://blog.oliverxu.cn
Author: oliverxu
Author-email: 273601727@qq.com
License: MIT
Keywords: Translation English2Chinese ClipBoard
Platform: linux
Classifier: Development Status :: 5 - Production/Stable
Classifier: Intended Audience :: Developers
Classifier: Natural Language :: Chinese (Simplified)
Classifier: Natural Language :: English
Classifier: Topic :: Utilities
Classifier: Topic :: Terminals
Classifier: Topic :: System :: Distributed Computing
Classifier: License :: OSI Approved :: MIT License
Classifier: Programming Language :: Python :: 2
Classifier: Programming Language :: Python :: 2.6
Classifier: Programming Language :: Python :: 2.7
Classifier: Programming Language :: Python :: 3
Classifier: Programming Language :: Python :: 3.3
Classifier: Programming Language :: Python :: 3.4
Classifier: Programming Language :: Python :: 3.5
Classifier: Programming Language :: Python :: 3.6
Requires-Dist: requests
Requires-Dist: pyperclip
Requires-Dist: dbus-python
Requires-Dist: notify2
